api/workspace/design.v
// =============================================================================
// design.v — 4-bit synchronous up-counter with synchronous reset
//
// Interface:
//   clk   — rising-edge clock
//   rst   — synchronous active-high reset (drives count to 0)
//   en    — count-enable; when low, counter holds its value
//   count — 4-bit output representing the current count value
// =============================================================================

`timescale 1ns / 1ps   // time unit = 1 ns, precision = 1 ps

module counter #(
    parameter WIDTH = 4          // configurable bit-width; default 4
)(
    input  wire             clk,
    input  wire             rst,
    input  wire             en,
    output reg  [WIDTH-1:0] count
);

    // Synchronous reset + enable
    always @(posedge clk) begin
        if (rst)
            count <= {WIDTH{1'b0}};   // reset: clear all bits
        else if (en)
            count <= count + 1'b1;    // count up on enabled clock edges
        // else: hold — implicit latch-free register hold in synchronous design
    end

endmodule

tb.v
// =============================================================================
// tb.v — Testbench for the 4-bit counter module
//
// What this testbench demonstrates:
//   • $dumpfile / $dumpvars  — VCD waveform generation (wave.vcd)
//   • Clock generation with always block
//   • Stimulus application with @(posedge clk) synchronisation
//   • $monitor for live signal tracing to stdout
//   • Assertion-style checks with $display and error counting
//   • Clean simulation termination with $finish
// =============================================================================

`timescale 1ns / 1ps

module tb_counter;

    // ── DUT port signals ──────────────────────────────────────────────────
    reg         clk;
    reg         rst;
    reg         en;
    wire [3:0]  count;

    // ── Error accumulator — non-zero at end means test FAILED ─────────────
    integer errors = 0;

    // ── Instantiate Design Under Test (DUT) ──────────────────────────────
    counter #(.WIDTH(4)) dut (
        .clk   (clk),
        .rst   (rst),
        .en    (en),
        .count (count)
    );

    // ── Clock generation — 10 ns period (100 MHz) ─────────────────────────
    initial clk = 1'b0;
    always  #5 clk = ~clk;   // toggle every 5 ns → full period = 10 ns

    // ── Waveform dump ─────────────────────────────────────────────────────
    // $dumpfile sets the output filename (must match VCD_FILE env var or default)
    // $dumpvars(0, tb_counter) dumps ALL signals in the entire hierarchy
    initial begin
        $dumpfile("wave.vcd");
        $dumpvars(0, tb_counter);
    end

    // ── Live signal monitor — prints whenever any listed signal changes ───
    initial begin
        $monitor("t=%0t | clk=%b rst=%b en=%b | count=%0d",
                 $time, clk, rst, en, count);
    end

    // ── Stimulus + self-checking ──────────────────────────────────────────
    initial begin
        $display("=== Counter Testbench Start ===");

        // --- Reset phase ---
        rst = 1; en = 0;
        repeat(3) @(posedge clk);     // hold reset for 3 cycles
        @(negedge clk);               // sample after falling edge for clean check
        if (count !== 4'd0) begin
            $display("FAIL [reset]: expected 0, got %0d", count);
            errors = errors + 1;
        end else begin
            $display("PASS [reset]: count = %0d", count);
        end

        // --- Enable counting ---
        @(posedge clk); rst = 0; en = 1;

        // Count from 0 to 15 (full 4-bit range) and check each value
        repeat(16) begin
            @(posedge clk);
        end
        // After 16 enabled rising edges from reset=0, count should have wrapped to 0
        @(negedge clk);
        if (count !== 4'd0) begin
            $display("FAIL [wrap]: expected 0 after wrap, got %0d", count);
            errors = errors + 1;
        end else begin
            $display("PASS [wrap]: count correctly wrapped to 0");
        end

        // --- Hold (enable low) ---
        en = 0;
        @(posedge clk); @(posedge clk);
        @(negedge clk);
        if (count !== 4'd0) begin
            $display("FAIL [hold]: count changed during en=0, got %0d", count);
            errors = errors + 1;
        end else begin
            $display("PASS [hold]: count held at 0 while en=0");
        end

        // --- Count a few and re-reset mid-stream ---
        en = 1;
        repeat(5) @(posedge clk);
        rst = 1;
        @(posedge clk);
        @(negedge clk);
        if (count !== 4'd0) begin
            $display("FAIL [mid-reset]: expected 0 after mid-stream reset, got %0d", count);
            errors = errors + 1;
        end else begin
            $display("PASS [mid-reset]: synchronous reset works mid-stream");
        end

        // ── Final result ──────────────────────────────────────────────────
        $display("=================================");
        if (errors == 0)
            $display("ALL TESTS PASSED");
        else
            $display("TESTS FAILED — %0d error(s)", errors);
        $display("=================================");

        $finish;   // cleanly ends simulation and flushes VCD
    end

endmodule

api/workspace/wave.vcd
$date
	Sun May 17 16:34:55 2026
$end
$version
	Icarus Verilog
$end
$timescale
	1ps
$end
$scope module tb_counter $end
$var wire 4 ! count [3:0] $end
$var reg 1 " clk $end
$var reg 1 # en $end
$var reg 1 $ rst $end
$var integer 32 % errors [31:0] $end
$scope module dut $end
$var wire 1 " clk $end
$var wire 1 # en $end
$var wire 1 $ rst $end
$var reg 4 & count [3:0] $end
$upscope $end
$upscope $end
$enddefinitions $end
#0
$dumpvars
bx &
b0 %
1$
0#
0"
bx !
$end
#5000
b0 !
b0 &
1"
#10000
0"
#15000
1"
#20000
0"
#25000
1"
#30000
0"
#35000
b1 !
b1 &
1#
0$
1"
#40000
0"
#45000
b10 !
b10 &
1"
#50000
0"
#55000
b11 !
b11 &
1"
#60000
0"
#65000
b100 !
b100 &
1"
#70000
0"
#75000
b101 !
b101 &
1"
#80000
0"
#85000
b110 !
b110 &
1"
#90000
0"
#95000
b111 !
b111 &
1"
#100000
0"
#105000
b1000 !
b1000 &
1"
#110000
0"
#115000
b1001 !
b1001 &
1"
#120000
0"
#125000
b1010 !
b1010 &
1"
#130000
0"
#135000
b1011 !
b1011 &
1"
#140000
0"
#145000
b1100 !
b1100 &
1"
#150000
0"
#155000
b1101 !
b1101 &
1"
#160000
0"
#165000
b1110 !
b1110 &
1"
#170000
0"
#175000
b1111 !
b1111 &
1"
#180000
0"
#185000
b0 !
b0 &
1"
#190000
0"
#195000
b1 !
b1 &
1"
#200000
0#
b1 %
0"
#205000
1"
#210000
0"
#215000
1"
#220000
1#
b10 %
0"
#225000
b10 !
b10 &
1"
#230000
0"
#235000
b11 !
b11 &
1"
#240000
0"
#245000
b100 !
b100 &
1"
#250000
0"
#255000
b101 !
b101 &
1"
#260000
0"
#265000
b0 !
b0 &
1$
1"
